HelloProject/__init__.py
HelloProject/hello.py
fispkg-1.0.0.dist-info/METADATA
fispkg-1.0.0.dist-info/WHEEL
fispkg-1.0.0.dist-info/top_level.txt
fispkg-1.0.0.dist-info/RECORD
